Workbook

Sheet Transactions
A1: txn_date | B1: description | C1: amount | D1: category | E1: note
A2: 01/09/2025 | B2: Mlinar | C2: -3.36 | D2: Dining & Restaurants
A3: 01/09/2025 | B3: Plodine | C3: -2.76 | D3: Groceries
A4: 01/09/2025 | B4: Naplata naknade za vođenje računa | C4: -3 | D4: Other
A5: 01/09/2025 | B5: U17357273 Dmytro Semeniuk | C5: -50 | D5: Investments
A6: 01/09/2025 | B6: Lidl | C6: -4.86 | D6: Groceries
A7: 02/09/2025 | B7: INA | C7: -20.01 | D7: Transportation
A8: 02/09/2025 | B8: SPAR Food & Fuel | C8: -0.85 | D8: Groceries
A9: 03/09/2025 | B9: AliExpress | C9: -8.64 | D9: Groceries
A10: 04/09/2025 | B10: Chatgpt | C10: -18.4 | D10: Entertainment & Subscriptions
A11: 05/09/2025 | B11: GOOGLE *YouTubePremium | C11: -3.06 | D11: Entertainment & Subscriptions
A12: 05/09/2025 | B12: UBER * EATS PENDING | C12: -18.64 | D12: Travelling
A13: 06/09/2025 | B13: PRTMN *KYIVSTAR T | C13: -2.05 | D13: Other
... A21: 15/09/2025 | B21: Bmove | C21: -0.6 | D21: Transportation
A22: 15/09/2025 | B22: Pu51000rijeka | C22: -15.5 | D22: Other | E22: Посилка словенцу
A23: 15/09/2025 | B23: Dante Bar | C23: -2.3 | D23: Coffee
A24: 15/09/2025 | B24: FlixBus | C24: -25.98 | D24: Travelling
A25: 15/09/2025 | B25: SPAR Food & Fuel | C25: -1.58 | D25: Groceries
A26: 15/09/2025 | B26: SPAR Food & Fuel | C26: -2.94 | D26: Groceries
A27: 16/09/2025 | B27: Restoran Kampus | C27: -1.88 | D27: Dining & Restaurants
A28: 17/09/2025 | B28: Mlinar | C28: -1.3 | D28: Dining & Restaurants
A29: 17/09/2025 | B29: Restoran Kampus | C29: -1.41 | D29: Dining & Restaurants
A30: 17/09/2025 | B30: Airbnb | C30: =-258.75/3 -> -86.25 | D30: Travelling | E30: Житло
A31: 17/09/2025 | B31: Gavranović | C31: -1.49 | D31: Groceries
A32: 17/09/2025 | B32: INA | C32: -20.08 | D32: Transportation
A33: 18/09/2025 | B33: Bmove | C33: -1 | D33: Transportation
A34: 19/09/2025 | B34: Gavranović | C34: -2.79 | D34: Groceries
A35: 19/09/2025 | B35: Plodine | C35: -0.44 | D35: Groceries
A36: 19/09/2025 | B36: Restoran Kampus | C36: -0.95 | D36: Dining & Restaurants
A37: 19/09/2025 | B37: dm drogerie | C37: -1.75 | D37: Other
A38: 20/09/2025 | B38: Rijeka Trans | C38: -30.02 | D38: Transportation
A39: 20/09/2025 | B39: KEKS Pay | C39: -2.3 | D39: Coffee
A40: 20/09/2025 | B40: SPAR Food & Fuel | C40: -1.09 | D40: Groceries
A41: 21/09/2025 | B41: Arriva | C41: -11.1 | D41: Travelling
A42: 22/09/2025 | B42: Transfer to ARTUR NASIROV | C42: -1 | D42: Other
... A54: 24/09/2025 | B54: Spar | C54: -2.44 | D54: Travelling
A55: 24/09/2025 | B55: Starbucks | C55: =-18.65/3 -> -6.2166667 | D55: Travelling
A56: 24/09/2025 | B56: Spar | C56: -2.1 | D56: Travelling
A57: 24/09/2025 | B57: Manna ABC | C57: -2.44 | D57: Travelling
A58: 25/09/2025 | B58: Noiret Biliárd & Darts Szalon | C58: =-11.72/2 -> -5.86 | D58: Travelling
A59: 25/09/2025 | B59: FlixBus | C59: -28.47 | D59: Travelling
A60: 25/09/2025 | B60: Duna Főnix Kft. | C60: =-45.53/3 -> -15.176667 | D60: Travelling
A61: 25/09/2025 | B61: Fortissimo Media | C61: -1.03 | D61: Travelling
A62: 25/09/2025 | B62: McDonald's | C62: -6.04 | D62: Travelling
A63: 25/09/2025 | B63: Spar | C63: -2.06 | D63: Travelling
A64: 25/09/2025 | B64: Spar | C64: -0.76 | D64: Travelling
A65: 25/09/2025 | B65: Lidl | C65: -4.17 | D65: Travelling
A66: 26/09/2025 | B66: Spar | C66: -3.01 | D66: Travelling
A67: 26/09/2025 | B67: Fitzkey Kurtoskalacs | C67: =-7.72/3 -> -2.5733333 | D67: Travelling
A68: 26/09/2025 | B68: Tesco | C68: -1.67 | D68: Travelling
A69: 26/09/2025 | B69: Anytime Bar & Entertainment | C69: =-7.45/2 -> -3.725 | D69: Travelling
A70: 26/09/2025 | B70: Davtom | C70: -1.17 | D70: Travelling
A71: 26/09/2025 | B71: Wolt | C71: =-13.45/2 -> -6.725 | D71: Travelling
A72: 26/09/2025 | B72: PayPal | C72: -2.22 | D72: Other
A73: 26/09/2025 | B73: Pizza Hut | C73: =-13.83/2 -> -6.915 | D73: Travelling
A74: 27/09/2025 | B74: Spar | C74: -3.73 | D74: Travelling
A75: 27/09/2025 | B75: Spar | C75: -2.75 | D75: Travelling
A76: 27/09/2025 | B76: Budapesti Közlekedési Központ - BKK | C76: -1.29 | D76: Travelling
A77: 27/09/2025 | B77: M7 Group | C77: -0.52 | D77: Travelling
A78: 27/09/2025 | B78: Klarna | C78: -0.78 | D78: Other
A79: 27/09/2025 | B79: McDonald's | C79: -4.44 | D79: Travelling
A80: 29/09/2025 | B80: Restoran Kampus | C80: -1.45 | D80: Dining & Restaurants
A81: 29/09/2025 | B81: KEKS Pay | C81: -2.3 | D81: Coffee
A82: 29/09/2025 | B82: McDonald's | C82: -2.6 | D82: Dining & Restaurants
A83: 29/09/2025 | B83: Plodine | C83: -1.1 | D83: Groceries
A84: 30/09/2025 | B84: SPAR Food & Fuel | C84: -2.18 | D84: Groceries
A85: 30/09/2025 | B85: INA | C85: -20.2 | D85: Transportation
A86: 45901 | B86: Bonnavia coffee | C86: -3 | D86: Coffee
A87: 45909 | B87: Bonnavia coffee | C87: -3 | D87: Coffee
A88: 45910 | B88: Bonnavia coffee | C88: -3 | D88: Coffee
A89: 45911 | B89: Bonnavia coffee | C89: -3 | D89: Coffee
A90: 45912 | B90: Кебаб в загребі | C90: -7 | D90: Dining & Restaurants
A91: 45916 | B91: Bonnavia coffee | C91: -3 | D91: Coffee
A92: 45917 | B92: Bonnavia coffee | C92: -3 | D92: Coffee
A93: 45929 | B93: Haircut | C93: -10 | D93: Other

Sheet Stats
A1: CASH | B1: 680
A2: ERSTE | B2: 92
A3: REVOLUT | B3: 168
A4: MONOBANK | B4: 0
A6: STOCKS INVESTMENTS | B6: 395
A7: CRYPTO INVESTMENTS | B7: 1052
A8: EMERGENCY FUND | B8: 400
A9: Savings | B9: 800 | C9: 200 євро на бінанс
A12: SPENT BY CATEGORIES
A13: Groceries | B13: =SUMIF(Table1[category],Stats!A13,Table1[amount]) -> -45.47
A14: Transportation | B14: =SUMIF(Table1[category],Stats!A14,Table1[amount]) -> -93.51
A15: Coffee | B15: =SUMIF(Table1[category],Stats!A15,Table1[amount]) -> -27.8
A16: Dining & Restaurants | B16: =SUMIF(Table1[category],Stats!A16,Table1[amount]) -> -23.93
A17: Shopping | B17: =SUMIF(Table1[category],Stats!A17,Table1[amount]) -> 0
A18: Home | B18: =SUMIF(Table1[category],Stats!A18,Table1[amount]) -> 0
A19: Cash Withdrawals | B19: =SUMIF(Table1[category],Stats!A19,Table1[amount]) -> 0
A20: Entertainment & Subscriptions | B20: =SUMIF(Table1[category],Stats!A20,Table1[amount]) -> -30.94
A21: Travelling | B21: =SUMIF(Table1[category],Stats!A21,Table1[amount]) -> -282.83167
A22: Education & Studying | B22: =SUMIF(Table1[category],Stats!A22,Table1[amount]) -> 0
A23: Other | B23: =SUMIF(Table1[category],Stats!A23,Table1[amount]) -> -44.1
A24: Investments | B24: =SUMIF(Table1[category],Stats!A24,Table1[amount]) -> -50
A26: Income | B26: =SUMIF(Table1[category],Stats!A26,Table1[amount]) -> 0
B27: =SUM(B13:B24) -> -598.58167
